ChemCal/__init__.py
ChemCal/_modidx.py
ChemCal/core.py
ChemCal-0.0.5.dist-info/LICENSE
ChemCal-0.0.5.dist-info/METADATA
ChemCal-0.0.5.dist-info/WHEEL
ChemCal-0.0.5.dist-info/entry_points.txt
ChemCal-0.0.5.dist-info/top_level.txt
ChemCal-0.0.5.dist-info/RECORD
